systemds/SystemDS.jar
systemds/__init__.py
systemds/project_info.py
systemds/conf/SystemDS-config-defaults.xml
systemds/conf/log4j.properties
systemds/context/__init__.py
systemds/context/systemds_context.py
systemds/examples/__init__.py
systemds/examples/tutorials/__init__.py
systemds/examples/tutorials/adult.py
systemds/examples/tutorials/mnist.py
systemds/lib/avro-1.11.2.jar
systemds/lib/avro-ipc-1.11.2.jar
systemds/lib/avro-mapred-1.11.2.jar
systemds/lib/commons-beanutils-1.9.4.jar
systemds/lib/commons-cli-1.2.jar
systemds/lib/commons-collections-3.2.2.jar
systemds/lib/commons-collections4-4.4.jar
systemds/lib/commons-compiler-3.1.9.jar
systemds/lib/commons-compress-1.23.0.jar
systemds/lib/commons-configuration2-2.8.0.jar
systemds/lib/commons-io-2.13.0.jar
systemds/lib/commons-lang3-3.12.0.jar
systemds/lib/commons-logging-1.1.3.jar
systemds/lib/commons-math3-3.4.1.jar
systemds/lib/commons-text-1.10.0.jar
systemds/lib/fastdoubleparser-0.9.0.jar
systemds/lib/guava-27.0-jre.jar
systemds/lib/hadoop-auth-3.3.6.jar
systemds/lib/hadoop-client-3.3.6.jar
systemds/lib/hadoop-common-3.3.6.jar
systemds/lib/hadoop-hdfs-3.3.6.jar
systemds/lib/hadoop-hdfs-client-3.3.6.jar
systemds/lib/hadoop-mapreduce-client-common-3.3.6.jar
systemds/lib/hadoop-mapreduce-client-core-3.3.6.jar
systemds/lib/hadoop-mapreduce-client-jobclient-3.3.6.jar
systemds/lib/hadoop-shaded-guava-1.1.1.jar
systemds/lib/hadoop-yarn-api-3.3.6.jar
systemds/lib/hadoop-yarn-client-3.3.6.jar
systemds/lib/hadoop-yarn-common-3.3.6.jar
systemds/lib/jackson-core-2.15.2.jar
systemds/lib/janino-3.1.9.jar
systemds/lib/log4j-api-2.22.1.jar
systemds/lib/log4j-core-2.22.1.jar
systemds/lib/netty-3.10.6.Final.jar
systemds/lib/netty-all-4.1.96.Final.jar
systemds/lib/netty-buffer-4.1.96.Final.jar
systemds/lib/netty-codec-4.1.96.Final.jar
systemds/lib/netty-codec-dns-4.1.96.Final.jar
systemds/lib/netty-codec-haproxy-4.1.96.Final.jar
systemds/lib/netty-codec-http-4.1.96.Final.jar
systemds/lib/netty-codec-http2-4.1.96.Final.jar
systemds-3.3.0.dist-info/LICENSE
systemds-3.3.0.dist-info/METADATA
systemds-3.3.0.dist-info/NOTICE
systemds-3.3.0.dist-info/WHEEL
systemds-3.3.0.dist-info/top_level.txt
systemds-3.3.0.dist-info/RECORD
