Metadata-Version: 2.2
Name: systemds
Version: 3.3.0
Summary: Apache SystemDS - An open source ML system for the end-to-end data science lifecycle
Home-page: https://github.com/apache/systemds
Author: SystemDS
Author-email: dev@systemds.apache.org
License: Apache 2.0
Platform: Microsoft :: Windows
Platform: POSIX
Platform: Unix
Platform: MacOS
Classifier: Intended Audience :: Developers
Classifier: Intended Audience :: Education
Classifier: Intended Audience :: Science/Research
Classifier: License :: OSI Approved :: Apache Software License
Classifier: Programming Language :: Python
Classifier: Programming Language :: Python :: 3
Classifier: Programming Language :: Python :: 3.6
Classifier: Programming Language :: Python :: 3.7
Classifier: Programming Language :: Python :: 3.8
Classifier: Programming Language :: Python :: 3 :: Only
Classifier: Topic :: Scientific/Engineering :: Mathematics
Classifier: Topic :: Software Development :: Libraries :: Python Modules
Classifier: Topic :: Software Development :: Libraries
Requires-Python: >=3.6
License-File: LICENSE
License-File: NOTICE
Requires-Dist: numpy>=1.8.2
Requires-Dist: py4j>=0.10.9
Requires-Dist: requests>=2.24.0
Requires-Dist: pandas>=1.2.2
Dynamic: author
Dynamic: author-email
Dynamic: classifier
Dynamic: description
Dynamic: description-content-type
Dynamic: home-page
Dynamic: license
Dynamic: platform
Dynamic: requires-dist
Dynamic: requires-python
Dynamic: summary
